CHANGES.txt
LICENSE.txt
MANIFEST.in
README.txt
setup.py
js/__init__.py
js.angular_ui_bootstrap.egg-info/PKG-INFO
js.angular_ui_bootstrap.egg-info/SOURCES.txt
js.angular_ui_bootstrap.egg-info/dependency_links.txt
js.angular_ui_bootstrap.egg-info/entry_points.txt
js.angular_ui_bootstrap.egg-info/namespace_packages.txt
js.angular_ui_bootstrap.egg-info/not-zip-safe
js.angular_ui_bootstrap.egg-info/requires.txt
js.angular_ui_bootstrap.egg-info/top_level.txt
js/angular_ui_bootstrap/__init__.py
js/angular_ui_bootstrap/resources/ui-bootstrap-tpls-0.6.0.js
js/angular_ui_bootstrap/resources/ui-bootstrap-tpls-0.6.0.min.js