Metadata-Version: 1.0
Name: js.angular-ui-bootstrap
Version: 0.6.0-1
Summary: Fanstatic packaging of Angular UI Boostrap
Home-page: https://github.com/abulte/js.angular_ui_bootstrap
Author: Alexandre Bulté
Author-email: alexandre@bulte.net
License: MIT
Platform: UNKNOWN
